<Database>
    <GameDBStringTable ID="LOC_IT_PATCH_1_0_13">
    
        <LanguageCode>it</LanguageCode>
        <LanguageNameLocalized>Italiano</LanguageNameLocalized>
        
        <Contributors>
            <Name>Oxymoron Games</Name>
        </Contributors>

        <!-- Note: feel free to rearrange any sentences with the parameter {1} so the word order makes sense -->
        <LocalizedStrings>
            
            <!-- RELATED FILE: StringTable[Language]Characters.xml -->
            
            <GameDBLocalizedString>      <LocID>ReservingAmbulance</LocID>                      <Text>In attesa dell'ambulanza</Text>  </GameDBLocalizedString>

            <!-- Note: used in second half of a sentence, lower-case is intentional -->
            <GameDBLocalizedString>      <LocID>WAITING_FOR_ROOM_EXM</LocID>                    <Text>in attesa di una sala visite libera</Text>  </GameDBLocalizedString>
            <GameDBLocalizedString>      <LocID>WAITING_FOR_ROOM_TRT</LocID>                    <Text>in attesa di una sala terapia libera</Text>  </GameDBLocalizedString>
            <GameDBLocalizedString>      <LocID>WAITING_FOR_ROOM_SURG</LocID>                   <Text>in attesa di una sala operatoria libera</Text>  </GameDBLocalizedString>
            <GameDBLocalizedString>      <LocID>WAITING_FOR_STAFF_EXM</LocID>                   <Text>in attesa di un medico/tecnico per l'esame</Text>  </GameDBLocalizedString>
            <GameDBLocalizedString>      <LocID>WAITING_FOR_STAFF_TRT</LocID>                   <Text>in attesa di un medico/tecnico per la terapia</Text>  </GameDBLocalizedString>
            <GameDBLocalizedString>      <LocID>WAITING_FOR_STAFF_SURG</LocID>                  <Text>in attesa dell'equipe chirurgica</Text>  </GameDBLocalizedString>
            <GameDBLocalizedString>      <LocID>WAITING_FOR_TRANSPORT_EXM</LocID>               <Text>in attesa del trasporto per l'esame</Text>  </GameDBLocalizedString>
            <GameDBLocalizedString>      <LocID>WAITING_FOR_TRANSPORT_TRT</LocID>               <Text>in attesa del trasporto per la terapia</Text>  </GameDBLocalizedString>
            <GameDBLocalizedString>      <LocID>WAITING_FOR_TRANSPORT_SURG</LocID>              <Text>in attesa del trasporto per l'operazione</Text>  </GameDBLocalizedString>
            <GameDBLocalizedString>      <LocID>WAITING_FOR_CRITICAL_PATIENTS</LocID>           <Text>dare la precedenza ai pazienti critici</Text>  </GameDBLocalizedString>

            <GameDBLocalizedString>      <LocID>SKIPPED_AFTER_LONG_WAIT</LocID>                 <Text>Annullamento dopo un'attesa troppo lunga</Text>  </GameDBLocalizedString>
            <GameDBLocalizedString>      <LocID>SCHEDULED_PROCEDURE_WAITING</LocID>             <Text>In programma</Text>  </GameDBLocalizedString>

            <GameDBLocalizedString>      <LocID>HOSPITALIZED_WaitingForBedFix</LocID>           <Text>in un letto senza l'attrezzatura necessaria</Text>  </GameDBLocalizedString>

            
            <!-- RELATED FILE: StringTable[Language]Notifications.xml -->

            <!-- Roles - for other usage in the UI see SEGMENT_HEADING_ROLES in StringTable[Language]UI.xml -->
            <!-- Roles - for the list of employee roles see EMPL_ROLE_EXM_TRT in StringTable[Language]Characters.xml -->
            <GameDBLocalizedString>      <LocID>NOTIF_NO_ROLES</LocID>                          <Text>Questo dipendente non ha alcun ruolo!</Text>  </GameDBLocalizedString>
            <GameDBLocalizedString>      <LocID>NOTIF_NO_ROLES_TEXT</LocID>                     <Text>Non è stato assegnato alcun ruolo a questo dipendente; resterà inattivo.</Text>  </GameDBLocalizedString>

            <!-- Workload - see UI_ROOM_USAGE_DAY in StringTable[Language]UI.xml -->
            <GameDBLocalizedString>      <LocID>NOTIF_ROOM_USAGE_STATS_DAY</LocID>              <Text>Statistiche carico di lavoro sala</Text>  </GameDBLocalizedString>
            <GameDBLocalizedString>      <LocID>NOTIF_ROOM_USAGE_STATS_DAY_TEXT</LocID>         <Text>Statistiche turno diurno:\nSale inattive: {1}\nSale con carico di lavoro critico: {2}</Text>  </GameDBLocalizedString>

            <GameDBLocalizedString>      <LocID>NOTIF_ROOM_USAGE_STATS_NIGHT</LocID>            <Text>Statistiche carico di lavoro sala</Text>  </GameDBLocalizedString>
            <GameDBLocalizedString>      <LocID>NOTIF_ROOM_USAGE_STATS_NIGHT_TEXT</LocID>       <Text>Statistiche turno notturno:\nSale inattive: {1}\nSale con carico di lavoro critico: {2}</Text>  </GameDBLocalizedString>

            <!-- Broken beds/rooms -->
            <!-- The room names filled in are from StringTable[Language]BuildingMode.xml, for example: -->
            <!-- ROOM_TYPE_ER_OBSERVATION_ROOM, ROOM_TYPE_INTENSIVE_CARE_UNIT, ROOM_TYPE_INPATIENT_WARD, ROOM_TYPE_HIGH_PRIORITY_INPATIENT_WARD -->
            <GameDBLocalizedString>      <LocID>NOTIF_HOSPITALIZED_PATIENT_BROKEN_BED</LocID>   <Text>Il letto del paziente si è rotto.</Text>  </GameDBLocalizedString>
            <GameDBLocalizedString>      <LocID>NOTIF_HOSPITALIZED_PATIENT_BROKEN_BED_TEXT</LocID><Text>Sistema il letto, altrimenti il paziente verrà trasferito in un altro letto disponibile, oppure verrà mandato via.</Text>  </GameDBLocalizedString>

            <GameDBLocalizedString>      <LocID>NOTIF_HOSPITALIZED_PATIENT_BED_TRANSFER</LocID>   <Text>Il paziente viene trasferito in un nuovo letto.</Text>  </GameDBLocalizedString>
            <GameDBLocalizedString>      <LocID>NOTIF_HOSPITALIZED_PATIENT_BED_TRANSFER_TEXT</LocID> <Text>Il letto del paziente si è rotto, perciò lo trasferiamo in un letto nuovo.</Text>  </GameDBLocalizedString>

            <GameDBLocalizedString>      <LocID>NOTIF_HOSPITALIZED_PATIENT_ROOM_TRANSFER_NEW_BED_WAIT</LocID>   <Text>Il paziente è in attesa di essere trasferito in un nuovo letto.</Text>  </GameDBLocalizedString>
            <GameDBLocalizedString>      <LocID>NOTIF_HOSPITALIZED_PATIENT_ROOM_TRANSFER_NEW_BED_WAIT_TEXT</LocID> <Text><![CDATA[Il letto del paziente si è rotto, perciò dobbiamo trasferirlo in un letto nuovo. Tuttavia, non ci sono letti liberi disponibili nella stanza <i>{1}</i>.]]></Text>  </GameDBLocalizedString>

            <GameDBLocalizedString>      <LocID>NOTIF_HOSPITALIZED_PATIENT_ROOM_NO_TRANSFER_NEW_BED_WAIT</LocID>   <Text>Il paziente è in attesa di essere trasferito in un nuovo letto.</Text>  </GameDBLocalizedString>
            <GameDBLocalizedString>      <LocID>NOTIF_HOSPITALIZED_PATIENT_ROOM_NO_TRANSFER_NEW_BED_WAIT_TEXT</LocID> <Text>Il letto del paziente si è rotto, perciò dobbiamo trasferirlo in un letto nuovo. Tuttavia, in questo momento non ci sono infermiere disponibili per trasportare il paziente.</Text>  </GameDBLocalizedString>

            <GameDBLocalizedString>      <LocID>NOTIF_HOSPITALIZED_PATIENT_ROOM_NO_TRANSFER_BED_WAIT</LocID>   <Text>Il paziente è in attesa di essere trasferito in una nuova stanza.</Text>  </GameDBLocalizedString>
            <GameDBLocalizedString>      <LocID>NOTIF_HOSPITALIZED_PATIENT_ROOM_NO_TRANSFER_BED_WAIT_TEXT</LocID> <Text><![CDATA[La stanza del paziente è rotta o non è disponibile, perciò dobbiamo trasferirlo nella stanza <i>{1}</i>. Tuttavia, in questo momento non ci sono infermiere disponibili per trasportare il paziente.]]></Text>  </GameDBLocalizedString>

            <GameDBLocalizedString>      <LocID>NOTIF_HOSPITALIZED_PATIENT_BROKEN_BED_TAKEN_AWAY</LocID>   <Text>Il paziente viene trasportato in un altro ospedale.</Text>  </GameDBLocalizedString>
            <GameDBLocalizedString>      <LocID>NOTIF_HOSPITALIZED_PATIENT_BROKEN_BED_TAKEN_AWAY_TEXT</LocID> <Text>Il letto del paziente è rimasto rotto troppo a lungo, perciò il paziente viene trasportato in un altro ospedale.</Text>  </GameDBLocalizedString>


            <!-- RELATED FILE: StringTable[Language]UI.xml -->

            <!-- Status column in table of patients -->
            <GameDBLocalizedString>      <LocID>TABLE_PATIENTS_STATUS</LocID>               <Text>Stato</Text>  </GameDBLocalizedString>
            
            <!-- Workload shown in department management mode for individual rooms (on the floor) -->
            <GameDBLocalizedString>      <LocID>WORKLOAD_NONE</LocID>                           <Text>Nessuno</Text>  </GameDBLocalizedString>
            <GameDBLocalizedString>      <LocID>WORKLOAD_LOW</LocID>                            <Text>Basso</Text>  </GameDBLocalizedString>
            <GameDBLocalizedString>      <LocID>WORKLOAD_MEDIUM</LocID>                         <Text>Medio</Text>  </GameDBLocalizedString>
            <GameDBLocalizedString>      <LocID>WORKLOAD_HIGH</LocID>                           <Text>Alto</Text>  </GameDBLocalizedString>
            <GameDBLocalizedString>      <LocID>WORKLOAD_CRITICAL</LocID>                       <Text>CRITICO</Text>  </GameDBLocalizedString>

            <!-- Marker of rooms extended outdoors in department management mode for individual rooms (on the floor) -->
            <GameDBLocalizedString>      <LocID>UI_ROOM_OUTDOORS</LocID>                        <Text>ALL'ESTERNO</Text>  </GameDBLocalizedString>
            
            <!-- Department management mode, neurology, on the right panel (hospitalization) -->
            <GameDBLocalizedString>      <LocID>LAB_TECHNOLOGIST_NEURO</LocID>                  <Text>Neurologo</Text>  </GameDBLocalizedString>

            
        </LocalizedStrings>
    </GameDBStringTable>
</Database>
   